Metadata-Version: 1.0
Name: scd-courses
Version: 0.2
Summary: currency exchange rates
Home-page: UNKNOWN
Author: UNKNOWN
Author-email: ivanbalashov2019@gmail.com
License: UNKNOWN
Platform: UNKNOWN
